MANIFEST.in
README.rst
setup.cfg
setup.py
pi/__init__.py
pi/__main__.py
pi/client.py
pi/config.py
pi/console.py
pi/environ.py
pi/images.py
pi/network.py
pi/resolve.py
pi/run.py
pi/services.py
pi/tasks.py
pi/types.py
pi/utils.py
pi/_requires/__init__.py
pi/_requires/six.py
pi/_requires/tabulate.py
pi/_requires/attr/__init__.py
pi/_requires/attr/_compat.py
pi/_requires/attr/_config.py
pi/_requires/attr/_funcs.py
pi/_requires/attr/_make.py
pi/_requires/attr/exceptions.py
pi/_requires/attr/filters.py
pi/_requires/attr/validators.py
pi/_requires/certifi/__init__.py
pi/_requires/certifi/__main__.py
pi/_requires/certifi/cacert.pem
pi/_requires/certifi/core.py
pi/_requires/certifi/old_root.pem
pi/_requires/certifi/weak.pem
pi/_requires/chardet/__init__.py
pi/_requires/chardet/big5freq.py
pi/_requires/chardet/big5prober.py
pi/_requires/chardet/chardistribution.py
pi/_requires/chardet/charsetgroupprober.py
pi/_requires/chardet/charsetprober.py
pi/_requires/chardet/codingstatemachine.py
pi/_requires/chardet/compat.py
pi/_requires/chardet/cp949prober.py
pi/_requires/chardet/enums.py
pi/_requires/chardet/escprober.py
pi/_requires/chardet/escsm.py
pi/_requires/chardet/eucjpprober.py
pi/_requires/chardet/euckrfreq.py
pi/_requires/chardet/euckrprober.py
pi/_requires/chardet/euctwfreq.py
pi/_requires/chardet/euctwprober.py
pi/_requires/chardet/gb2312freq.py
pi/_requires/chardet/gb2312prober.py
pi/_requires/chardet/hebrewprober.py
pi/_requires/chardet/jisfreq.py
pi/_requires/chardet/jpcntx.py
pi/_requires/chardet/langbulgarianmodel.py
pi/_requires/chardet/langcyrillicmodel.py
pi/_requires/chardet/langgreekmodel.py
pi/_requires/chardet/langhebrewmodel.py
pi/_requires/chardet/langhungarianmodel.py
pi/_requires/chardet/langthaimodel.py
pi/_requires/chardet/langturkishmodel.py
pi/_requires/chardet/latin1prober.py
pi/_requires/chardet/mbcharsetprober.py
pi/_requires/chardet/mbcsgroupprober.py
pi/_requires/chardet/mbcssm.py
pi/_requires/chardet/sbcharsetprober.py
pi_env.egg-info/PKG-INFO
pi_env.egg-info/SOURCES.txt
pi_env.egg-info/dependency_links.txt
pi_env.egg-info/entry_points.txt
pi_env.egg-info/top_level.txt