Metadata-Version: 1.0
Name: pi-env
Version: 0.1.1
Summary: Command-line interface for your projects
Home-page: https://github.com/vmagamedov/pi
Author: Vladimir Magamedov
Author-email: vladimir@magamedov.com
License: BSD
Platform: UNKNOWN
